OData1C/__init__.py
OData1C/connection.py
OData1C/exceptions.py
OData1C/models.py
OData1C/odata/__init__.py
OData1C/odata/manager.py
OData1C/odata/query.py
odata1c_client-0.1.3.dist-info/METADATA
odata1c_client-0.1.3.dist-info/WHEEL
odata1c_client-0.1.3.dist-info/RECORD
