Metadata-Version: 2.1
Name: odata1c-client
Version: 0.1.3
Summary: A Python client for interacting with 1C systems via OData v3, providing ORM-like functionality, data validation, and query construction.
License: MIT
Author: Vladislav Akashev
Author-email: vlad.akashev.w@gmail.com
Requires-Python: >=3.12,<4.0
Classifier: License :: OSI Approved :: MIT License
Classifier: Programming Language :: Python :: 3
Classifier: Programming Language :: Python :: 3.12
Classifier: Programming Language :: Python :: 3.13
Requires-Dist: pydantic (==2.7.0)
Requires-Dist: requests (==2.32.3)
